odoo/addons/analytic_partner/README.rst
odoo/addons/analytic_partner/__init__.py
odoo/addons/analytic_partner/__manifest__.py
odoo/addons/analytic_partner/i18n/analytic_partner.pot
odoo/addons/analytic_partner/i18n/ar.po
odoo/addons/analytic_partner/i18n/bg.po
odoo/addons/analytic_partner/i18n/bs.po
odoo/addons/analytic_partner/i18n/ca.po
odoo/addons/analytic_partner/i18n/cs.po
odoo/addons/analytic_partner/i18n/cs_CZ.po
odoo/addons/analytic_partner/i18n/de.po
odoo/addons/analytic_partner/i18n/el_GR.po
odoo/addons/analytic_partner/i18n/en_GB.po
odoo/addons/analytic_partner/i18n/es.po
odoo/addons/analytic_partner/i18n/es_CR.po
odoo/addons/analytic_partner/i18n/es_EC.po
odoo/addons/analytic_partner/i18n/es_MX.po
odoo/addons/analytic_partner/i18n/et.po
odoo/addons/analytic_partner/i18n/eu.po
odoo/addons/analytic_partner/i18n/fi.po
odoo/addons/analytic_partner/i18n/fr.po
odoo/addons/analytic_partner/i18n/fr_CA.po
odoo/addons/analytic_partner/i18n/fr_CH.po
odoo/addons/analytic_partner/i18n/fr_FR.po
odoo/addons/analytic_partner/i18n/gl.po
odoo/addons/analytic_partner/i18n/hr.po
odoo/addons/analytic_partner/i18n/hr_HR.po
odoo/addons/analytic_partner/i18n/hu.po
odoo/addons/analytic_partner/i18n/id.po
odoo/addons/analytic_partner/i18n/it.po
odoo/addons/analytic_partner/i18n/ja.po
odoo/addons/analytic_partner/i18n/lt.po
odoo/addons/analytic_partner/i18n/mk.po
odoo/addons/analytic_partner/i18n/mn.po
odoo/addons/analytic_partner/i18n/nb.po
odoo/addons/analytic_partner/i18n/nb_NO.po
odoo/addons/analytic_partner/i18n/nl.po
odoo/addons/analytic_partner/i18n/nl_BE.po
odoo/addons/analytic_partner/i18n/pl.po
odoo/addons/analytic_partner/i18n/pt.po
odoo/addons/analytic_partner/i18n/pt_BR.po
odoo/addons/analytic_partner/i18n/pt_PT.po
odoo/addons/analytic_partner/i18n/ro.po
odoo/addons/analytic_partner/i18n/ru.po
odoo/addons/analytic_partner/i18n/sk_SK.po
odoo/addons/analytic_partner/i18n/sl.po
odoo/addons/analytic_partner/i18n/sv.po
odoo/addons/analytic_partner/i18n/th.po
odoo_addon_analytic_partner-17.0.1.0.0.2.dist-info/METADATA
odoo_addon_analytic_partner-17.0.1.0.0.2.dist-info/WHEEL
odoo_addon_analytic_partner-17.0.1.0.0.2.dist-info/top_level.txt
odoo_addon_analytic_partner-17.0.1.0.0.2.dist-info/RECORD
